kissats/__init__.py
kissats/ats_client.py
kissats/ats_resource.py
kissats/basic_runner.py
kissats/common.py
kissats/exceptions.py
kissats/task.py
kissats/task_pack.py
kissats/schemas/__init__.py
kissats/schemas/global_param_in_schema.yaml
kissats/schemas/reporting_schema.yaml
kissats/schemas/schemas.py
kissats/schemas/task_param_schema.yaml
kissats/schemas/task_return_schema.yaml
kissats-1.0.0a5.dist-info/METADATA
kissats-1.0.0a5.dist-info/RECORD
kissats-1.0.0a5.dist-info/WHEEL
kissats-1.0.0a5.dist-info/top_level.txt
